thinking_hats_ai/__init__.py
thinking_hats_ai/brainstorming_session.py
thinking_hats_ai/hats/black.py
thinking_hats_ai/hats/blue.py
thinking_hats_ai/hats/green.py
thinking_hats_ai/hats/hats.py
thinking_hats_ai/hats/red.py
thinking_hats_ai/hats/white.py
thinking_hats_ai/hats/yellow.py
thinking_hats_ai/prompting_techniques/base_technique.py
thinking_hats_ai/prompting_techniques/chain_of_thought.py
thinking_hats_ai/prompting_techniques/chain_of_verification.py
thinking_hats_ai/prompting_techniques/chaining.py
thinking_hats_ai/prompting_techniques/contrastive_prompting.py
thinking_hats_ai/prompting_techniques/emotion_prompt.py
thinking_hats_ai/prompting_techniques/few_shot.py
thinking_hats_ai/prompting_techniques/multi_agent.py
thinking_hats_ai/prompting_techniques/persona_pattern.py
thinking_hats_ai/prompting_techniques/re_act.py
thinking_hats_ai/prompting_techniques/system_2_attention.py
thinking_hats_ai/prompting_techniques/take_a_step_back.py
thinking_hats_ai/prompting_techniques/technique.py
thinking_hats_ai/prompting_techniques/zero_shot_cot.py
thinking_hats_ai/tools/black_hat.py
thinking_hats_ai/tools/blue_hat.py
thinking_hats_ai/tools/green_hat.py
thinking_hats_ai/tools/red_hat.py
thinking_hats_ai/tools/tools.py
thinking_hats_ai/tools/white_hat.py
thinking_hats_ai/tools/yellow_hat.py
thinking_hats_ai/utils/api_handler.py
thinking_hats_ai/utils/brainstorming_input.py
thinking_hats_ai/utils/logger.py
thinking_hats_ai/utils/string_utils.py
thinking_hats_ai-1.2.1.dist-info/METADATA
thinking_hats_ai-1.2.1.dist-info/WHEEL
thinking_hats_ai-1.2.1.dist-info/RECORD
