Metadata-Version: 2.4
Name: thinking-hats-ai
Version: 1.2.1
Summary: thinking-hats-ai is a Python package that facilitates idea generation by following Edward de Bono's Six Thinking Hats methodology from his Book. It enables you to generate ideas by selecting one of the six hats and lets you choose one of the implemented prompting technique to follow while generating the idea.
Author: Three Thinking Hats
Requires-Python: >=3.9
Requires-Dist: ag2[openai]>=0.8.5
Requires-Dist: autogen>=0.8.5
Requires-Dist: langchain-community
Requires-Dist: langchain-openai
Requires-Dist: langchain>=0.3.20
Requires-Dist: urllib3<2.0.0
